aquarel/__init__.py
aquarel/theme.py
aquarel/transforms.py
aquarel/utils.py
aquarel/themes/ambivalent.json
aquarel/themes/arctic_dark.json
aquarel/themes/arctic_light.json
aquarel/themes/boxy_dark.json
aquarel/themes/boxy_light.json
aquarel/themes/gruvbox_dark.json
aquarel/themes/gruvbox_light.json
aquarel/themes/minimal_dark.json
aquarel/themes/minimal_light.json
aquarel/themes/scientific.json
aquarel/themes/solarized_dark.json
aquarel/themes/solarized_light.json
aquarel/themes/umbra_dark.json
aquarel/themes/umbra_light.json
aquarel-0.0.7.dist-info/LICENSE
aquarel-0.0.7.dist-info/METADATA
aquarel-0.0.7.dist-info/WHEEL
aquarel-0.0.7.dist-info/top_level.txt
aquarel-0.0.7.dist-info/RECORD
