Metadata-Version: 2.2
Name: aquarel
Version: 0.0.7
Summary: Lightweight templating engine for matplotlib
Home-page: https://github.com/lgienapp/aquarel
Download-URL: https://github.com/lgienapp/aquarel/archive/refs/tags/v0.0.7.tar.gz
Author: Lukas Gienapp
Author-email: lukas@gien.app
License: MIT
Project-URL: Bug Tracker, https://github.com/lgienapp/aquarel/issues
Keywords: theme,plotting,visualization,styling,matplotlib
Classifier: Development Status :: 4 - Beta
Classifier: Intended Audience :: Developers
Classifier: Topic :: Multimedia :: Graphics :: Presentation
Classifier: Topic :: Scientific/Engineering :: Visualization
Classifier: Topic :: Artistic Software
Classifier: License :: OSI Approved :: MIT License
Classifier: Programming Language :: Python :: 3
Requires-Python: >3.7
License-File: LICENSE
Requires-Dist: matplotlib>=3.4.0
Requires-Dist: cycler
Requires-Dist: seaborn
Dynamic: author
Dynamic: author-email
Dynamic: classifier
Dynamic: description
Dynamic: description-content-type
Dynamic: download-url
Dynamic: home-page
Dynamic: keywords
Dynamic: license
Dynamic: project-url
Dynamic: requires-dist
Dynamic: requires-python
Dynamic: summary
